plugandpie/__init__.py
plugandpie/discovery.py
plugandpie/plugnplay.py
plugandpie/common/__init__.py
plugandpie/common/i2c.py
plugandpie/common/utils.py
plugandpie/device/Accelerometer.py
plugandpie/device/Device.py
plugandpie/device/DeviceBuilder.py
plugandpie/device/Positiometer.py
plugandpie/device/Proxy.py
plugandpie/device/Thermometer.py
plugandpie/device/__init__.py
plugandpie/devices/Device.py
plugandpie/devices/__init__.py
plugandpie/devices/mapping.py
plugandpie/devices/accelerometer/Accelerometer.py
plugandpie/devices/accelerometer/MMA8452Q.py
plugandpie/devices/accelerometer/__init__.py
plugandpie/drivers/LSM9DS0.py
plugandpie/drivers/MMA8452Q.py
plugandpie/drivers/__init__.py
plugandpie/drivers/__model__.py
plugandpie/drivers/mapping.py
plugandpie/drivers/accelerometers/MMA8452Q.py
plugandpie/drivers/accelerometers/__init__.py
plugandpie/interface/I2C.py
plugandpie/interface/Interface.py
plugandpie/interface/SMBus.py
plugandpie/interface/SPI.py
plugandpie/interface/__init__.py
plugandpie/interfaces/I2C.py
plugandpie/interfaces/Interface.py
plugandpie/interfaces/SMBus.py
plugandpie/interfaces/SPI.py
plugandpie/interfaces/Serial.py
plugandpie/interfaces/__init__.py
plugandpie/interfaces/__model__.py
plugandpie/sensors/Accelerometer.py
plugandpie/sensors/Gyroscope.py
plugandpie/sensors/Magnetometer.py
plugandpie/sensors/Positiometer.py
plugandpie/sensors/Thermometer.py
plugandpie/sensors/__init__.py
plugandpie/sensors/__model__.py
plugandpie-0.1a7.dist-info/DESCRIPTION.rst
plugandpie-0.1a7.dist-info/METADATA
plugandpie-0.1a7.dist-info/RECORD
plugandpie-0.1a7.dist-info/WHEEL
plugandpie-0.1a7.dist-info/metadata.json
plugandpie-0.1a7.dist-info/top_level.txt
tests/__init__.py
