Metadata-Version: 2.0
Name: plugandpie
Version: 0.1a7
Summary: Device driver and automation for common sensors
Home-page: https://github.com/villasv/plugandpie
Author: Victor Villas
Author-email: villasv@outlook.com
License: GPLv3+
Keywords: plugandpie plug and play raspberry pi sensors
Platform: UNKNOWN
Classifier: License :: OSI Approved :: GNU General Public License v3 or later (GPLv3+)
Classifier: Programming Language :: Python :: 3.5
Classifier: Programming Language :: Python :: 2.7
Classifier: Development Status :: 3 - Alpha 
Classifier: Intended Audience :: Developers
Classifier: Intended Audience :: Education
Classifier: Topic :: Software Development :: Libraries :: Python Modules
Requires-Dist: enum34; python_version < "3.4"
